setup.py
bino_guss_distribution/Binomialdistribution.py
bino_guss_distribution/Gaussiandistribution.py
bino_guss_distribution/Generaldistribution.py
bino_guss_distribution/__init__.py
bino_guss_distribution.egg-info/PKG-INFO
bino_guss_distribution.egg-info/SOURCES.txt
bino_guss_distribution.egg-info/dependency_links.txt
bino_guss_distribution.egg-info/not-zip-safe
bino_guss_distribution.egg-info/top_level.txt