Metadata-Version: 2.1
Name: bino-guss-distribution
Version: 0.1
Summary: Gaussian and binomial distributions
Home-page: UNKNOWN
Author: subham jyoti
Author-email: subhamjyoti1@gmail.com
License: UNKNOWN
Platform: UNKNOWN
